docs/README.md
hledger_lots/__init__.py
hledger_lots/__main__.py
hledger_lots/avg.py
hledger_lots/avg_info.py
hledger_lots/checks.py
hledger_lots/cli.py
hledger_lots/commodity_tag.py
hledger_lots/fifo.py
hledger_lots/fifo_info.py
hledger_lots/files.py
hledger_lots/hl.py
hledger_lots/info.py
hledger_lots/lib.py
hledger_lots/options.py
hledger_lots/prices_yahoo.py
hledger_lots/prompt.py
hledger_lots/prompt_buy.py
hledger_lots/prompt_sell.py
tests/__init__.py
tests/lots_data.py
tests/test__main__.py
tests/test_avg.py
tests/test_checks.py
tests/test_fifo.py
tests/test_files.py
tests/test_hl.py
tests/test_info.py
tests/test_lib.py
venv/bin/rst2html.py
venv/bin/rst2html4.py
venv/bin/rst2html5.py
venv/bin/rst2latex.py
venv/bin/rst2man.py
venv/bin/rst2odt.py
venv/bin/rst2odt_prepstyles.py
venv/bin/rst2pseudoxml.py
venv/bin/rst2s5.py
venv/bin/rst2xetex.py
venv/bin/rst2xml.py
venv/bin/rstpep2html.py
hledger_lots-0.4.2.dist-info/METADATA
hledger_lots-0.4.2.dist-info/WHEEL
hledger_lots-0.4.2.dist-info/entry_points.txt
hledger_lots-0.4.2.dist-info/top_level.txt
hledger_lots-0.4.2.dist-info/RECORD
