Metadata-Version: 2.1
Name: hledger-lots
Version: 0.4.2
License: MIT License
Project-URL: homepage, https://github.com/edkedk99/hledger-lots
Project-URL: documentation, https://edkedk99.github.io/hledger-lots/
Project-URL: repository, https://github.com/edkedk99/hledger-lots
Requires-Python: >=3.8
Requires-Dist: click
Requires-Dist: rich-click
Requires-Dist: tabulate
Requires-Dist: pyxirr
Requires-Dist: yfinance
Requires-Dist: requests
Requires-Dist: requests-cache
Requires-Dist: questionary
